Workbook

Sheet Assumptions
A1: Solar + Battery + Grid Compute Site — assumptions (edit yellow)
A2: A 4MW grid IMPORT connection guarantees 24/7/365 power (so ~90% GPU utilisation — fixes the seasonal mismatch). Solar + LFP battery cut the power COST, not the utilisation.
A4: SITE
A5: Grid IMPORT connection (MW) | B5: 4
A6: Compute load (MW) | B6: 4
A7: Solar array (MWp) | B7: 8
A8: LFP battery usable (MWh, 1 cycle/day) | B8: 8
A9: Utilisation (grid-backed) | B9: 0.9
A10: Daylight window (h, when solar offsets load) | B10: 12
A12: POWER PRICES (p/kWh)
A13: Solar LCOE (your panels' £/kWh) | B13: 4 | C13: UK ground-mount solar ~£30–50/MWh
A14: Grid NIGHT / off-peak | B14: 13 | C14: Economy-7 / wholesale night ~10–14p
A15: Grid DAY / peak | B15: 25
A16: Battery amortisation per kWh cycled | B16: 4.6 | C16: LFP £250/kWh ÷ 6,000 cycles ÷ 0.9 ≈ 4.6p
A17: Battery round-trip efficiency | B17: 0.9
A20: COMPUTE (the 3-year consumable)
A21: Compute capex £/MW (chips+servers+heat) | B21: 5630000
A22: Revenue £/MWh of power drawn (contracted) | B22: 560 | C22: £560/MWh = contracted £0.25/hr per 0.45kW GPU. SPOT is far lower — see note.
A23: Maintenance (% capex/yr) | B23: 0.05
A24: Other opex £/MW/yr | B24: 30000
A25: Chip ECONOMIC life (yrs) — payback MUST beat this | B25: 3 | C25: V100 (8yr) now rents $0.02/hr — chips die economically at ~3 yr
A27: ENERGY INFRASTRUCTURE (the 25-year durable asset)
A28: Solar capex £/MWp | B28: 600000
A29: LFP battery capex £/MWh | B29: 250000
A30: Grid connection capex £ | B30: 1000000

Sheet Monthly Energy
A1: UK year, month by month — where the power comes from (all MWh)
A2: Solar serves daytime load first; surplus charges the battery; battery covers evening; grid (cheap night / peak day) backstops. Live off Assumptions.
A4: Month | B4: Days | C4: PSH | D4: Solar gen | E4: Day load | F4: Night load | G4: Solar→day | H4: Surplus | I4: →Battery | J4: Curtailed | K4: Batt→night | L4: Grid day | M4: Grid night | N4: Cost £
A5: Jan | B5: 31 | C5: 0.74 | D5: =Assumptions!$B$7*C5*B5 | E5: =Assumptions!$B$6*Assumptions!$B$10*Assumptions!$B$9*B5 | F5: =Assumptions!$B$6*(24-Assumptions!$B$10)*Assumptions!$B$9*B5 | G5: =MIN(D5,E5) | H5: =MAX(0,D5-E5) | I5: =MIN(H5,Assumptions!$B$8*B5) | J5: =H5-I5 | K5: =I5*Assumptions!$B$17 | L5: =E5-G5 | M5: =MAX(0,F5-K5) | N5: =((G5+I5)*Assumptions!$B$13+K5*Assumptions!$B$16+L5*Assumptions!$B$15+M5*Assumptions!$B$14)*10
A6: Feb | B6: 28 | C6: 1.36 | D6: =Assumptions!$B$7*C6*B6 | E6: =Assumptions!$B$6*Assumptions!$B$10*Assumptions!$B$9*B6 | F6: =Assumptions!$B$6*(24-Assumptions!$B$10)*Assumptions!$B$9*B6 | G6: =MIN(D6,E6) | H6: =MAX(0,D6-E6) | I6: =MIN(H6,Assumptions!$B$8*B6) | J6: =H6-I6 | K6: =I6*Assumptions!$B$17 | L6: =E6-G6 | M6: =MAX(0,F6-K6) | N6: =((G6+I6)*Assumptions!$B$13+K6*Assumptions!$B$16+L6*Assumptions!$B$15+M6*Assumptions!$B$14)*10
A7: Mar | B7: 31 | C7: 2.31 | D7: =Assumptions!$B$7*C7*B7 | E7: =Assumptions!$B$6*Assumptions!$B$10*Assumptions!$B$9*B7 | F7: =Assumptions!$B$6*(24-Assumptions!$B$10)*Assumptions!$B$9*B7 | G7: =MIN(D7,E7) | H7: =MAX(0,D7-E7) | I7: =MIN(H7,Assumptions!$B$8*B7) | J7: =H7-I7 | K7: =I7*Assumptions!$B$17 | L7: =E7-G7 | M7: =MAX(0,F7-K7) | N7: =((G7+I7)*Assumptions!$B$13+K7*Assumptions!$B$16+L7*Assumptions!$B$15+M7*Assumptions!$B$14)*10
A8: Apr | B8: 30 | C8: 3.42 | D8: =Assumptions!$B$7*C8*B8 | E8: =Assumptions!$B$6*Assumptions!$B$10*Assumptions!$B$9*B8 | F8: =Assumptions!$B$6*(24-Assumptions!$B$10)*Assumptions!$B$9*B8 | G8: =MIN(D8,E8) | H8: =MAX(0,D8-E8) | I8: =MIN(H8,Assumptions!$B$8*B8) | J8: =H8-I8 | K8: =I8*Assumptions!$B$17 | L8: =E8-G8 | M8: =MAX(0,F8-K8) | N8: =((G8+I8)*Assumptions!$B$13+K8*Assumptions!$B$16+L8*Assumptions!$B$15+M8*Assumptions!$B$14)*10
A9: May | B9: 31 | C9: 4.38 | D9: =Assumptions!$B$7*C9*B9 | E9: =Assumptions!$B$6*Assumptions!$B$10*Assumptions!$B$9*B9 | F9: =Assumptions!$B$6*(24-Assumptions!$B$10)*Assumptions!$B$9*B9 | G9: =MIN(D9,E9) | H9: =MAX(0,D9-E9) | I9: =MIN(H9,Assumptions!$B$8*B9) | J9: =H9-I9 | K9: =I9*Assumptions!$B$17 | L9: =E9-G9 | M9: =MAX(0,F9-K9) | N9: =((G9+I9)*Assumptions!$B$13+K9*Assumptions!$B$16+L9*Assumptions!$B$15+M9*Assumptions!$B$14)*10
A10: Jun | B10: 30 | C10: 4.5 | D10: =Assumptions!$B$7*C10*B10 | E10: =Assumptions!$B$6*Assumptions!$B$10*Assumptions!$B$9*B10 | F10: =Assumptions!$B$6*(24-Assumptions!$B$10)*Assumptions!$B$9*B10 | G10: =MIN(D10,E10) | H10: =MAX(0,D10-E10) | I10: =MIN(H10,Assumptions!$B$8*B10) | J10: =H10-I10 | K10: =I10*Assumptions!$B$17 | L10: =E10-G10 | M10: =MAX(0,F10-K10) | N10: =((G10+I10)*Assumptions!$B$13+K10*Assumptions!$B$16+L10*Assumptions!$B$15+M10*Assumptions!$B$14)*10
A11: Jul | B11: 31 | C11: 4.35 | D11: =Assumptions!$B$7*C11*B11 | E11: =Assumptions!$B$6*Assumptions!$B$10*Assumptions!$B$9*B11 | F11: =Assumptions!$B$6*(24-Assumptions!$B$10)*Assumptions!$B$9*B11 | G11: =MIN(D11,E11) | H11: =MAX(0,D11-E11) | I11: =MIN(H11,Assumptions!$B$8*B11) | J11: =H11-I11 | K11: =I11*Assumptions!$B$17 | L11: =E11-G11 | M11: =MAX(0,F11-K11) | N11: =((G11+I11)*Assumptions!$B$13+K11*Assumptions!$B$16+L11*Assumptions!$B$15+M11*Assumptions!$B$14)*10
A12: Aug | B12: 31 | C12: 3.78 | D12: =Assumptions!$B$7*C12*B12 | E12: =Assumptions!$B$6*Assumptions!$B$10*Assumptions!$B$9*B12 | F12: =Assumptions!$B$6*(24-Assumptions!$B$10)*Assumptions!$B$9*B12 | G12: =MIN(D12,E12) | H12: =MAX(0,D12-E12) | I12: =MIN(H12,Assumptions!$B$8*B12) | J12: =H12-I12 | K12: =I12*Assumptions!$B$17 | L12: =E12-G12 | M12: =MAX(0,F12-K12) | N12: =((G12+I12)*Assumptions!$B$13+K12*Assumptions!$B$16+L12*Assumptions!$B$15+M12*Assumptions!$B$14)*10
A13: Sep | B13: 30 | C13: 2.82 | D13: =Assumptions!$B$7*C13*B13 | E13: =Assumptions!$B$6*Assumptions!$B$10*Assumptions!$B$9*B13 | F13: =Assumptions!$B$6*(24-Assumptions!$B$10)*Assumptions!$B$9*B13 | G13: =MIN(D13,E13) | H13: =MAX(0,D13-E13) | I13: =MIN(H13,Assumptions!$B$8*B13) | J13: =H13-I13 | K13: =I13*Assumptions!$B$17 | L13: =E13-G13 | M13: =MAX(0,F13-K13) | N13: =((G13+I13)*Assumptions!$B$13+K13*Assumptions!$B$16+L13*Assumptions!$B$15+M13*Assumptions!$B$14)*10
A14: Oct | B14: 31 | C14: 1.61 | D14: =Assumptions!$B$7*C14*B14 | E14: =Assumptions!$B$6*Assumptions!$B$10*Assumptions!$B$9*B14 | F14: =Assumptions!$B$6*(24-Assumptions!$B$10)*Assumptions!$B$9*B14 | G14: =MIN(D14,E14) | H14: =MAX(0,D14-E14) | I14: =MIN(H14,Assumptions!$B$8*B14) | J14: =H14-I14 | K14: =I14*Assumptions!$B$17 | L14: =E14-G14 | M14: =MAX(0,F14-K14) | N14: =((G14+I14)*Assumptions!$B$13+K14*Assumptions!$B$16+L14*Assumptions!$B$15+M14*Assumptions!$B$14)*10
A15: Nov | B15: 30 | C15: 0.86 | D15: =Assumptions!$B$7*C15*B15 | E15: =Assumptions!$B$6*Assumptions!$B$10*Assumptions!$B$9*B15 | F15: =Assumptions!$B$6*(24-Assumptions!$B$10)*Assumptions!$B$9*B15 | G15: =MIN(D15,E15) | H15: =MAX(0,D15-E15) | I15: =MIN(H15,Assumptions!$B$8*B15) | J15: =H15-I15 | K15: =I15*Assumptions!$B$17 | L15: =E15-G15 | M15: =MAX(0,F15-K15) | N15: =((G15+I15)*Assumptions!$B$13+K15*Assumptions!$B$16+L15*Assumptions!$B$15+M15*Assumptions!$B$14)*10
A16: Dec | B16: 31 | C16: 0.6 | D16: =Assumptions!$B$7*C16*B16 | E16: =Assumptions!$B$6*Assumptions!$B$10*Assumptions!$B$9*B16 | F16: =Assumptions!$B$6*(24-Assumptions!$B$10)*Assumptions!$B$9*B16 | G16: =MIN(D16,E16) | H16: =MAX(0,D16-E16) | I16: =MIN(H16,Assumptions!$B$8*B16) | J16: =H16-I16 | K16: =I16*Assumptions!$B$17 | L16: =E16-G16 | M16: =MAX(0,F16-K16) | N16: =((G16+I16)*Assumptions!$B$13+K16*Assumptions!$B$16+L16*Assumptions!$B$15+M16*Assumptions!$B$14)*10
A17: TOTAL | D17: =SUM(D5:D16) | E17: =SUM(E5:E16) | F17: =SUM(F5:F16) | G17: =SUM(G5:G16) | H17: =SUM(H5:H16) | I17: =SUM(I5:I16) | J17: =SUM(J5:J16) | K17: =SUM(K5:K16) | ... N17: =SUM(N5:N16)
A19: Blended power cost (p/kWh) | D19: =N17/((E17+F17)*10)
A20: Solar self-consumed (%) | D20: =(G17+I17)/D17
A21: Curtailed solar (% of gen) — wasted | D21: =J17/D17

Sheet Economics
A1: Economics — two assets: 3-yr chips on 25-yr energy infrastructure
A3: POWER (from the monthly sim)
A4: Power drawn (MWh/yr) | B4: =('Monthly Energy'!$E$17+'Monthly Energy'!$F$17)
A5: Blended power cost (p/kWh) | B5: ='Monthly Energy'!$D$19 | C5: vs 25p naive grid / ~19p smart all-grid
A6: Annual power bill £ | B6: ='Monthly Energy'!$N$17
A8: COMPUTE LAYER (3-yr chips)
A9: Compute capex £ (load × £/MW) | B9: =Assumptions!B6*Assumptions!B21
A10: Revenue £/yr (contracted) | B10: =B4*Assumptions!B22
A11: − Power bill | B11: =-B6
A12: − Maintenance | B12: =-B9*Assumptions!B23
A13: − Other opex | B13: =-Assumptions!B6*Assumptions!B24
A14: NET £/yr | B14: =B10+B11+B12+B13
A15: Compute PAYBACK (months) | B15: =IF(B14>0,B9/B14*12,"loss")
A16: Chip economic life (months) | B16: =Assumptions!B25*12
A17: Verdict vs chip life | B17: =IF(B15<Assumptions!B25*12*0.8,"OK — profit window",IF(B15<Assumptions!B25*12,"TIGHT","FAILS — chip dies first"))
A19: ENERGY INFRASTRUCTURE LAYER (25-yr durable asset)
A20: Solar capex £ | B20: =Assumptions!B7*Assumptions!B28
A21: Battery capex £ | B21: =Assumptions!B8*Assumptions!B29
A22: Grid connection capex £ | B22: =Assumptions!B30
A23: Energy infra capex £ (total) | B23: =B20+B21+B22
A24: Power saving vs 19p smart-grid £/yr | B24: =(19-B5)*B4*10
A25: Energy infra payback (yrs) — 25-yr life | B25: =IF(B24>0,B23/B24,"none")
A27: WHOLE SITE
A28: Total capex £ (compute + energy) | B28: =B9+B23
A29: Net £/yr (after power, before energy-infra amort) | B29: =B14
A31: THE CATCH: revenue assumes you have SOLD all this compute at contracted rates (~90% util). You do NOT have that demand yet — it is the single biggest assumption. At SPOT/typical rates (~55% util, lower £/MWh) the revenue roughly HALVES and payback blows past chip life.

Sheet Solar Sweep
A1: How much solar to pair with the 4MW connection? (battery 8MWh, 90% util)
A2: More solar → cheaper power, but past ~2× the load you curtail (waste) summer surplus without a bigger battery or export. Static snapshot; the live model is on 'Monthly Energy'.
A4: Solar (MWp) | B4: Blended p/kWh | C4: Curtailed % | D4: Save vs 25p grid £/yr | E4: Save vs 19p grid £/yr | F4: Solar:load ratio
A5: 0 | B5: 19 | C5: 0 | D5: 1892160 | E5: 0 | F5: 0.0×
A6: 4 | B6: 16.5 | C6: 0 | D6: 2679198 | E6: 787038 | F6: 1.0×
A7: 8 | B7: 14 | C7: 0 | D7: 3466236 | E7: 1574076 | F7: 2.0×
A8: 12 | B8: 12.1 | C8: 0.013977978 | D8: 4080234 | E8: 2188074 | F8: 3.0×
A9: 16 | B9: 11.2 | C9: 0.14494904 | D9: 4360479 | E9: 2468319 | F9: 4.0×
A10: 20 | B10: 10.6 | C10: 0.25778323 | D10: 4541383 | E10: 2649223 | F10: 5.0×
A12: SWEET SPOT: ~6–10 MWp (1.5–2.5× the load) self-consumes nearly all generation with a modest battery. Beyond that you need either a much bigger (expensive) battery or an export connection to avoid wasting summer sun.
A14: KEY INSIGHT: if you already have CHEAP NIGHT GRID (~13p), a big battery is hard to justify — the grid is a cheaper 'battery' than a battery. The physical battery earns its keep mainly by capturing summer solar surplus and shaving peak-day grid. Size it small.

Sheet Notes & Sources
A1: Notes & Sources
A3: CHIP LIFE — the binding constraint
A4: GPU rental rate collapses ~80–95% over 5–6 yrs | B4: V100 (2017) now $0.02/hr; 2080 Ti (2018) $0.11/hr — economic life ~3 yr
A5: → compute must pay back inside ~3 yr | B5: Energy infra (solar/battery/grid) is the 25-yr durable asset; chips are a rolling 3-yr consumable
A6: BATTERY — which and why
A7: LFP (lithium iron phosphate) is the right chemistry | B7: Cheapest, safest, ~6,000-cycle life for daily solar-shift. £200–350/kWh installed (UK 2026)
A8: Size it SMALL with a grid connection | B8: Cheap night grid (~13p) is a cheaper 'store' than a battery (~9p delivered BUT huge capex). Battery's job: capture summer surplus + shave peak day
A9: SOLAR
A10: UK ground-mount LCOE ~£30–50/MWh (3–5p) | B10: ~937 kWh/kWp/yr; 10–11% capacity factor; summer ~8× winter output
A11: Pair ~1.5–2.5× the load | B11: Beyond that, curtailment without bigger battery or export
A12: THE MODEL'S LOAD-BEARING ASSUMPTION
A13: Revenue assumes CONTRACTED demand at ~90% util | B13: You do NOT have this. Spot/typical demand ≈ half the revenue and breaks the payback. This is the bet, not the power.
A14: Grid IMPORT connection is the unlock | B14: A small import connection (for winter/nights) is far easier to get than a big EXPORT connection — that is the real edge for queue-blocked solar
A15: SOURCES
A16: UK solar irradiance / PSH by month | B16: https://re.jrc.ec.europa.eu/pvg_tools/en/
A17: UK grid connection queue / curtailment | B17: https://www.nationalgrideso.com/industry-information/connections
A18: LFP grid battery costs 2026 | B18: https://www.nrel.gov/analysis/tech-cost-analysis.html
A19: Vast.ai per-GPU rates (V100/2080Ti collapse) | B19: https://vast.ai/pricing/gpu/TESLA-V100
