Workbook

Sheet Assumptions
A1: Compute-Heat Brick — Indoor Private Pool Model
A2: Edit the YELLOW cells. Everything recalculates. All GBP, June 2026. GREEN = computed.
A4: OPERATING ASSUMPTIONS
A5: Occupancy / utilisation (fraction of time earning) | B5: 0.55 | C5: THE make-or-break number — measure it with one box
A6: Electricity price you pay (p/kWh) | B6: 20
A7: FX ($ per £) | B7: 1.27
A8: Vast renter premium (host keeps 1 ÷ this) | B8: 1.25 | C8: Vast's renter price ≈ 25% above host earnings → host keeps ~80%
A9: Maintenance (% of capex / yr) | B9: 0.05
A10: Other opex (£/box/yr: monitoring, platform, support) | B10: 150
A11: Hours per year | B11: 8760
A12: GPUs per box (pool box) | B12: 6
A14: REVENUE ASSUMPTIONS (see 'Revenue vs GPU' tab)
A15: Revenue method | B15: Rental
A16: Token price (£ / million tokens, if Token) | B16: 0.4 | C16: commodity ~£0.03 · mid ~£0.15 · reliable-fleet ~£0.55+
A18: POOL (HOST) ASSUMPTIONS
A19: Indoor pool heat demand (kW) | B19: 7 | C19: mid indoor pool ~5–10 kW
A20: Heat value displaced for host (p/kWh) | B20: 8 | C20: gas ~8 · pool heat-pump ~5.5 · electric ~25
A22: SELECTED GPU (drives Unit Economics)
A23: GPU model | B23: RTX 4090 | C23: pick any of the 12 below — Unit Economics recomputes
A25: GPU RETURN-ON-CAPITAL — 12 cards worth costing, audited 7 Jun 2026, ranked best-first
A26: GPU | B26: Used £ | C26: Heat W | D26: Renter $/hr (typ) | E26: tok/s | F26: Occ % | G26: Host £/hr | H26: Net £/yr | I26: ROC %/yr | J26: Payback | K26: New £ | L26: Vast headline $/hr | M26: confidence | N26: price | O26: rate
A27: A100 80GB SXM | B27: 4000 | C27: 400 | D27: 0.85 | E27: 115 | F27: 0.55 | G27: =D27/$B$8/$B$7 | H27: =G27*F27*$B$11-(C27/1000)*$B$11*F27*($B$6/100) | I27: =H27/B27 | J27: =IF(H27>0,B27/H27*12,"never") | K27: 6500 | L27: 0.97 | M27: price MOD / rate MOD | N27: price | O27: rate
A28: A100 40GB PCIe | B28: 3500 | C28: 250 | D28: 0.6 | E28: 110 | F28: 0.55 | G28: =D28/$B$8/$B$7 | H28: =G28*F28*$B$11-(C28/1000)*$B$11*F28*($B$6/100) | I28: =H28/B28 | J28: =IF(H28>0,B28/H28*12,"never") | K28: 5500 | L28: 0.64 | M28: price LOW / rate MOD | N28: price | O28: rate
A29: RTX 5090 | B29: 3270 | C29: 575 | D29: 0.65 | E29: 140 | F29: 0.55 | G29: =D29/$B$8/$B$7 | H29: =G29*F29*$B$11-(C29/1000)*$B$11*F29*($B$6/100) | I29: =H29/B29 | J29: =IF(H29>0,B29/H29*12,"never") | K29: 3599 | L29: 0.8 | M29: price HIGH / rate LOW-MOD | N29: price | O29: rate
A30: RTX 4090 | B30: 1843 | C30: 450 | D30: 0.4 | E30: 120 | F30: 0.55 | G30: =D30/$B$8/$B$7 | H30: =G30*F30*$B$11-(C30/1000)*$B$11*F30*($B$6/100) | I30: =H30/B30 | J30: =IF(H30>0,B30/H30*12,"never") | K30: 1804 | L30: 0.58 | M30: price HIGH / rate MOD | N30: price | O30: rate
A31: NVIDIA L4 | B31: 1550 | C31: 72 | D31: 0.29 | E31: 43 | F31: 0.35 | G31: =D31/$B$8/$B$7 | H31: =G31*F31*$B$11-(C31/1000)*$B$11*F31*($B$6/100) | I31: =H31/B31 | J31: =IF(H31>0,B31/H31*12,"never") | K31: 2200 | L31: 0.29 | M31: price MOD / rate HIGH | N31: price | O31: rate
A32: H100 80GB PCIe | B32: 18000 | C32: 350 | D32: 2 | E32: 280 | F32: 0.55 | G32: =D32/$B$8/$B$7 | H32: =G32*F32*$B$11-(C32/1000)*$B$11*F32*($B$6/100) | I32: =H32/B32 | J32: =IF(H32>0,B32/H32*12,"never") | K32: 25000 | L32: 2.13 | M32: price LOW / rate HIGH | N32: price | O32: rate
A33: RTX 3090 | B33: 820 | C33: 350 | D33: 0.24 | E33: 95 | F33: 0.35 | G33: =D33/$B$8/$B$7 | H33: =G33*F33*$B$11-(C33/1000)*$B$11*F33*($B$6/100) | I33: =H33/B33 | J33: =IF(H33>0,B33/H33*12,"never") | K33: 2180 | L33: 0.3 | M33: price HIGH / rate MOD | N33: price | O33: rate
A34: RTX A6000 | B34: 2900 | C34: 300 | D34: 0.39 | E34: 100 | F34: 0.45 | G34: =D34/$B$8/$B$7 | H34: =G34*F34*$B$11-(C34/1000)*$B$11*F34*($B$6/100) | I34: =H34/B34 | J34: =IF(H34>0,B34/H34*12,"never") | K34: 3500 | L34: 0.39 | M34: price MOD / rate HIGH | N34: price | O34: rate
A35: A10 | B35: 1700 | C35: 150 | D35: 0.26 | E35: 70 | F35: 0.35 | G35: =D35/$B$8/$B$7 | H35: =G35*F35*$B$11-(C35/1000)*$B$11*F35*($B$6/100) | I35: =H35/B35 | J35: =IF(H35>0,B35/H35*12,"never") | K35: 2545 | L35: 0.32 | M35: price MOD / rate MOD | N35: price | O35: rate
A36: RTX A5000 | B36: 1100 | C36: 230 | D36: 0.2 | E36: 75 | F36: 0.35 | G36: =D36/$B$8/$B$7 | H36: =G36*F36*$B$11-(C36/1000)*$B$11*F36*($B$6/100) | I36: =H36/B36 | J36: =IF(H36>0,B36/H36*12,"never") | K36: 1900 | L36: 0.23 | M36: price MOD / rate HIGH | N36: price | O36: rate
A37: L40S | B37: 5200 | C37: 350 | D37: 0.47 | E37: 115 | F37: 0.55 | G37: =D37/$B$8/$B$7 | H37: =G37*F37*$B$11-(C37/1000)*$B$11*F37*($B$6/100) | I37: =H37/B37 | J37: =IF(H37>0,B37/H37*12,"never") | K37: 7130 | L37: 0.47 | M37: price MOD / rate MOD | N37: price | O37: rate
A38: A40 | B38: 3800 | C38: 300 | D38: 0.3 | E38: 90 | F38: 0.35 | G38: =D38/$B$8/$B$7 | H38: =G38*F38*$B$11-(C38/1000)*$B$11*F38*($B$6/100) | I38: =H38/B38 | J38: =IF(H38>0,B38/H38*12,"never") | K38: 5100 | L38: 0.32 | M38: price MOD / rate MOD | N38: price | O38: rate
A39: ROC %/yr = Net ÷ Used £ (the 'highest return on capital' ranking you asked for). Host £/hr = Renter $/hr ÷ 1.25 (Vast renter premium) ÷ 1.27 (FX). RENTER $/hr is the TYPICAL achieved rate (multi-source), NOT Vast's headline (shown for reference) — Vast's page price is a ceiling. Occ (yellow) = reasoned estimate; Vast publishes none — MEASURE it. Prices audited 7 Jun 2026 (bestvaluegpu.com + UK resellers).
A40: Excluded: every sub-16GB / obsolete card (3060/3070/3080/4060Ti/4070/4080/5070/5080/2080Ti/V100/T4) — all LOSE money after electricity (renters won't hire <16GB VRAM). Not a data gap; they are out of contention.

Sheet Capital Cost (BoM)
A1: Capital Cost — full bill of materials, per pool box (heat recovery REQUIRED)
A2: Yellow = editable unit price. Qty auto-scales with GPUs/box (Assumptions!B12). Heat-recovery lines are mandatory — they ARE the host's free heat.
A4: Item | B4: Unit £ | C4: Qty | D4: Line £ | E4: Source
A5: COMPUTE + HOST
A6: GPU (selected) | B6: =VLOOKUP(Assumptions!$B$23,Assumptions!$A$27:$P$38,2,FALSE) | C6: =Assumptions!$B$12 | D6: =B6*C6 | E6: bestvaluegpu
A7: PCIe riser cable (per GPU) | B7: 20 | C7: =Assumptions!$B$12 | D7: =B7*C7 | E7: Amazon UK
A8: Chassis (4U GPU case) | B8: 110 | C8: 1 | D8: =B8*C8 | E8: Scan UK
A9: PSU 1600W 80+ (1 per ~4 GPUs) | B9: 300 | C9: =ROUNDUP(Assumptions!$B$12/4,0) | D9: =B9*C9 | E9: Scan UK
A10: Mainboard (multi-PCIe) | B10: 290 | C10: 1 | D10: =B10*C10 | E10: idealo
A11: CPU (host, Ryzen 9) | B11: 270 | C11: 1 | D11: =B11*C11 | E11: idealo
A12: RAM 32GB DDR5 | B12: 90 | C12: 1 | D12: =B12*C12 | E12: Amazon UK
A13: NVMe 1TB (model-weight cache) | B13: 140 | C13: 1 | D13: =B13*C13 | E13: PriceSpy
A14: Networking NIC 2.5GbE | B14: 15 | C14: 1 | D14: =B14*C14 | E14: Amazon UK
A15: Node controller (Raspberry Pi 5) | B15: 80 | C15: 1 | D15: =B15*C15 | E15: idealo
A16: HEAT RECOVERY (required — this is the host's free heat)
A17: GPU water block (per GPU) | B17: 180 | C17: =Assumptions!$B$12 | D17: =B17*C17 | E17: EKWB / WatercoolingUK
A18: Brazed-plate heat exchanger (to pool) | B18: 80 | C18: 1 | D18: =B18*C18 | E18: eBay UK
A19: Circulation pump (D5) | B19: 89 | C19: 1 | D19: =B19*C19 | E19: WatercoolingUK
A20: Coolant + tubing + fittings + reservoir | B20: 120 | C20: 1 | D20: =B20*C20 | E20: Amazon / WatercoolingUK
A21: METERING + INSTALL
A22: MID revenue submeter (electricity reimbursement) | B22: 100 | C22: 1 | D22: =B22*C22 | E22: smartprocess / TEW
A23: Install — electrical (dedicated circuit / load mgmt) | B23: 450 | C23: 1 | D23: =B23*C23 | E23: electrician (BS 7671)
A24: Install — pool plumbing (HX into pool loop) | B24: 500 | C24: 1 | D24: =B24*C24 | E24: SPATA pool installer
A26: TOTAL CAPEX per box | D26: =SUM(D6:D24)
A28: Heat-recovery + pool-install lines are mandatory — without them there is no heat to give the host, so no site.

Sheet Revenue vs GPU
A1: GPU Cost-Benefit — every Vast.ai model, corrected host rate (ranked by payback)
A2: Host £/hr = Renter $/hr ÷ premium (Assumptions!B8) ÷ FX (Assumptions!B7). Net = rental revenue − electricity (paid only while computing). Per-card occupancy from Assumptions col F. This is the table that drives card choice: high VRAM cards earn, sub-16GB cards sit idle.
A4: GPU | B4: Buy £ | C4: Heat W | D4: Occ % | E4: Renter $/hr | F4: Host $/hr | G4: Host £/hr | H4: Rental £/yr | I4: Elec £/yr | J4: NET £/yr | K4: Payback yr | L4: Net £/yr per kW heat | M4: tok/s
A5: =Assumptions!A27 | B5: =Assumptions!B27 | C5: =Assumptions!C27 | D5: =Assumptions!F27 | E5: =Assumptions!D27 | F5: =Assumptions!D27/Assumptions!$B$8 | G5: =F5/Assumptions!$B$7 | H5: =G5*Assumptions!F27*Assumptions!$B$11 | I5: =(Assumptions!C27/1000)*Assumptions!$B$11*Assumptions!F27*(Assumptions!$B$6/100) | J5: =H5-I5 | K5: =IF(J5>0,B5/J5,"never") | L5: =J5/(Assumptions!C27/1000) | M5: =Assumptions!E27
A6: =Assumptions!A28 | B6: =Assumptions!B28 | C6: =Assumptions!C28 | D6: =Assumptions!F28 | E6: =Assumptions!D28 | F6: =Assumptions!D28/Assumptions!$B$8 | G6: =F6/Assumptions!$B$7 | H6: =G6*Assumptions!F28*Assumptions!$B$11 | I6: =(Assumptions!C28/1000)*Assumptions!$B$11*Assumptions!F28*(Assumptions!$B$6/100) | J6: =H6-I6 | K6: =IF(J6>0,B6/J6,"never") | L6: =J6/(Assumptions!C28/1000) | M6: =Assumptions!E28
A7: =Assumptions!A29 | B7: =Assumptions!B29 | C7: =Assumptions!C29 | D7: =Assumptions!F29 | E7: =Assumptions!D29 | F7: =Assumptions!D29/Assumptions!$B$8 | G7: =F7/Assumptions!$B$7 | H7: =G7*Assumptions!F29*Assumptions!$B$11 | I7: =(Assumptions!C29/1000)*Assumptions!$B$11*Assumptions!F29*(Assumptions!$B$6/100) | J7: =H7-I7 | K7: =IF(J7>0,B7/J7,"never") | L7: =J7/(Assumptions!C29/1000) | M7: =Assumptions!E29
A8: =Assumptions!A30 | B8: =Assumptions!B30 | C8: =Assumptions!C30 | D8: =Assumptions!F30 | E8: =Assumptions!D30 | F8: =Assumptions!D30/Assumptions!$B$8 | G8: =F8/Assumptions!$B$7 | H8: =G8*Assumptions!F30*Assumptions!$B$11 | I8: =(Assumptions!C30/1000)*Assumptions!$B$11*Assumptions!F30*(Assumptions!$B$6/100) | J8: =H8-I8 | K8: =IF(J8>0,B8/J8,"never") | L8: =J8/(Assumptions!C30/1000) | M8: =Assumptions!E30
A9: =Assumptions!A31 | B9: =Assumptions!B31 | C9: =Assumptions!C31 | D9: =Assumptions!F31 | E9: =Assumptions!D31 | F9: =Assumptions!D31/Assumptions!$B$8 | G9: =F9/Assumptions!$B$7 | H9: =G9*Assumptions!F31*Assumptions!$B$11 | I9: =(Assumptions!C31/1000)*Assumptions!$B$11*Assumptions!F31*(Assumptions!$B$6/100) | J9: =H9-I9 | K9: =IF(J9>0,B9/J9,"never") | L9: =J9/(Assumptions!C31/1000) | M9: =Assumptions!E31
A10: =Assumptions!A32 | B10: =Assumptions!B32 | C10: =Assumptions!C32 | D10: =Assumptions!F32 | E10: =Assumptions!D32 | F10: =Assumptions!D32/Assumptions!$B$8 | G10: =F10/Assumptions!$B$7 | H10: =G10*Assumptions!F32*Assumptions!$B$11 | I10: =(Assumptions!C32/1000)*Assumptions!$B$11*Assumptions!F32*(Assumptions!$B$6/100) | J10: =H10-I10 | K10: =IF(J10>0,B10/J10,"never") | L10: =J10/(Assumptions!C32/1000) | M10: =Assumptions!E32
A11: =Assumptions!A33 | B11: =Assumptions!B33 | C11: =Assumptions!C33 | D11: =Assumptions!F33 | E11: =Assumptions!D33 | F11: =Assumptions!D33/Assumptions!$B$8 | G11: =F11/Assumptions!$B$7 | H11: =G11*Assumptions!F33*Assumptions!$B$11 | I11: =(Assumptions!C33/1000)*Assumptions!$B$11*Assumptions!F33*(Assumptions!$B$6/100) | J11: =H11-I11 | K11: =IF(J11>0,B11/J11,"never") | L11: =J11/(Assumptions!C33/1000) | M11: =Assumptions!E33
A12: =Assumptions!A34 | B12: =Assumptions!B34 | C12: =Assumptions!C34 | D12: =Assumptions!F34 | E12: =Assumptions!D34 | F12: =Assumptions!D34/Assumptions!$B$8 | G12: =F12/Assumptions!$B$7 | H12: =G12*Assumptions!F34*Assumptions!$B$11 | I12: =(Assumptions!C34/1000)*Assumptions!$B$11*Assumptions!F34*(Assumptions!$B$6/100) | J12: =H12-I12 | K12: =IF(J12>0,B12/J12,"never") | L12: =J12/(Assumptions!C34/1000) | M12: =Assumptions!E34
A13: =Assumptions!A35 | B13: =Assumptions!B35 | C13: =Assumptions!C35 | D13: =Assumptions!F35 | E13: =Assumptions!D35 | F13: =Assumptions!D35/Assumptions!$B$8 | G13: =F13/Assumptions!$B$7 | H13: =G13*Assumptions!F35*Assumptions!$B$11 | I13: =(Assumptions!C35/1000)*Assumptions!$B$11*Assumptions!F35*(Assumptions!$B$6/100) | J13: =H13-I13 | K13: =IF(J13>0,B13/J13,"never") | L13: =J13/(Assumptions!C35/1000) | M13: =Assumptions!E35
A14: =Assumptions!A36 | B14: =Assumptions!B36 | C14: =Assumptions!C36 | D14: =Assumptions!F36 | E14: =Assumptions!D36 | F14: =Assumptions!D36/Assumptions!$B$8 | G14: =F14/Assumptions!$B$7 | H14: =G14*Assumptions!F36*Assumptions!$B$11 | I14: =(Assumptions!C36/1000)*Assumptions!$B$11*Assumptions!F36*(Assumptions!$B$6/100) | J14: =H14-I14 | K14: =IF(J14>0,B14/J14,"never") | L14: =J14/(Assumptions!C36/1000) | M14: =Assumptions!E36
A15: =Assumptions!A37 | B15: =Assumptions!B37 | C15: =Assumptions!C37 | D15: =Assumptions!F37 | E15: =Assumptions!D37 | F15: =Assumptions!D37/Assumptions!$B$8 | G15: =F15/Assumptions!$B$7 | H15: =G15*Assumptions!F37*Assumptions!$B$11 | I15: =(Assumptions!C37/1000)*Assumptions!$B$11*Assumptions!F37*(Assumptions!$B$6/100) | J15: =H15-I15 | K15: =IF(J15>0,B15/J15,"never") | L15: =J15/(Assumptions!C37/1000) | M15: =Assumptions!E37
A16: =Assumptions!A38 | B16: =Assumptions!B38 | C16: =Assumptions!C38 | D16: =Assumptions!F38 | E16: =Assumptions!D38 | F16: =Assumptions!D38/Assumptions!$B$8 | G16: =F16/Assumptions!$B$7 | H16: =G16*Assumptions!F38*Assumptions!$B$11 | I16: =(Assumptions!C38/1000)*Assumptions!$B$11*Assumptions!F38*(Assumptions!$B$6/100) | J16: =H16-I16 | K16: =IF(J16>0,B16/J16,"never") | L16: =J16/(Assumptions!C38/1000) | M16: =Assumptions!E38
A18: Read it as: a card must EARN (≥24GB VRAM → real occupancy) AND make real HEAT (high TDP) to suit a heat-recovery box. The 4090/5090 win on both; sub-16GB cards lose money after electricity.

Sheet Unit Economics
A1: Per-Box Unit Economics — indoor pool box (selected GPU × GPUs/box)
A3: CONFIGURATION
A4: GPU | B4: =Assumptions!B23
A5: GPUs per box | B5: =Assumptions!B12
A6: Revenue method | B6: =Assumptions!B15
A7: Renter $/hr per GPU (typical achieved, not Vast headline) | B7: =VLOOKUP(Assumptions!B23,Assumptions!$A$27:$P$38,4,FALSE)
A8: Host £/hr per GPU (after ÷1.25 ÷FX) | B8: =B7/Assumptions!B8/Assumptions!B7
A9: tok/s per GPU | B9: =VLOOKUP(Assumptions!B23,Assumptions!$A$27:$P$38,5,FALSE)
A10: TDP per GPU (W = heat) | B10: =VLOOKUP(Assumptions!B23,Assumptions!$A$27:$P$38,3,FALSE)
A12: CAPITAL
A13: TOTAL CAPEX per box (from BoM) | B13: ='Capital Cost (BoM)'!$D$26
A15: ANNUAL P&L (£/yr)
A16: Power draw (kW) | B16: =B5*B10/1000
A17: Revenue — rental (corrected host rate) | B17: =B5*B8*Assumptions!B5*Assumptions!B11
A18: Revenue — token | B18: =B5*B9*3600*Assumptions!B11*Assumptions!B5/1000000*Assumptions!B16
A19: Revenue — selected method | B19: =IF(Assumptions!B15="Token",B18,B17)
A20: Electricity (you pay) | B20: =B16*Assumptions!B11*Assumptions!B5*(Assumptions!B6/100)
A21: Maintenance | B21: =Assumptions!B9*B13
A22: Other opex | B22: =Assumptions!B10
A23: NET PROFIT | B23: =B19-B20-B21-B22
A25: RETURNS
A26: Payback (years) | B26: =IF(B23>0,B13/B23,"loss")
A27: Return on capital (%/yr) | B27: =IF(B13>0,B23/B13,0)
A29: HEAT TO THE POOL (free to host — not your revenue)
A30: Heat output (kW, util-weighted avg) | B30: =B16*Assumptions!B5
A31: Heat output (kWh/yr) | B31: =B16*Assumptions!B11*Assumptions!B5
A32: Value to pool owner (£/yr) | B32: =B31*(Assumptions!B20/100)
A33: Boxes to meet pool's heat demand | B33: =ROUNDUP(Assumptions!B19/MAX(B30,0.01),0)

Sheet Pool Model
A1: Indoor Private Pool — the deployment we're focusing on
A3: THE POOL (host)
A4: Pool heat demand (kW) | B4: =Assumptions!B19
A5: Pool heating cost today (£/yr, indoor) | B5: 3500 | C5: indoor pool ~£2,500–4,000/yr
A6: Heat we deliver per box (kW avg) | B6: ='Unit Economics'!B30
A7: Boxes per pool (to match demand) | B7: =ROUNDUP(B4/MAX(B6,0.01),0)
A8: GPUs per pool | B8: =B7*Assumptions!B12
A10: VALUE TO THE POOL OWNER
A11: Free heat delivered (£/yr) | B11: =B7*'Unit Economics'!B32
A12: ≈ share of their heating bill covered | B12: =IF(B5>0,MIN(1,B11/B5),0)
A14: VALUE TO YOU (per pool)
A15: Capex per pool | B15: =B7*'Unit Economics'!B13
A16: Net profit per pool (£/yr) | B16: =B7*'Unit Economics'!B23
A17: Payback (years) | B17: =IF(B16>0,B15/B16,"loss")
A19: MARKET
A20: UK indoor pools (addressable) | B20: ~30,000–50,000
A21: Channel | B21: SPATA pool installers/servicers | C21: spata.co.uk
A22: Incumbent to watch (commercial pools) | B22: Deep Green (£200M, Octopus) | C22: Data Centre Dynamics
A24: Pool economics sources: | B24: Origin (indoor running cost)
B25: Poolstore (heating cost)
B26: HeatPumps4Pools (COP, sizing)

Sheet Utilisation Sensitivity
A1: Payback (years) vs Occupancy — per pool box (selected GPU, full BoM capex, corrected host rate)
A3: Occupancy → | B3: 0.25 | C3: 0.4 | D3: 0.5 | E3: 0.6 | F3: 0.7 | G3: 0.9
A4: Payback (selected GPU) | B4: =IF((('Unit Economics'!$B$5*'Unit Economics'!$B$8*0.25*Assumptions!$B$11)-('Unit Economics'!$B$16*Assumptions!$B$11*0.25*(Assumptions!$B$6/100))-Assumptions!$B$9*'Unit Economics'!$B$13-Assumptions!$B$10)>0,'Unit Economics'!$B$13/(('Unit Economics'!$B$5*'Unit Economics'!$B$8*0.25*Assumptions!$B$11)-('Unit Economics'!$B$16*Assumptions!$B$11*0.25*(Assumptions!$B$6/100))-Assumptions!$B$9*'Unit Economics'!$B$13-Assumptions!$B$10),"loss") | C4: =IF((('Unit Economics'!$B$5*'Unit Economics'!$B$8*0.4*Assumptions!$B$11)-('Unit Economics'!$B$16*Assumptions!$B$11*0.4*(Assumptions!$B$6/100))-Assumptions!$B$9*'Unit Economics'!$B$13-Assumptions!$B$10)>0,'Unit Economics'!$B$13/(('Unit Economics'!$B$5*'Unit Economics'!$B$8*0.4*Assumptions!$B$11)-('Unit Economics'!$B$16*Assumptions!$B$11*0.4*(Assumptions!$B$6/100))-Assumptions!$B$9*'Unit Economics'!$B$13-Assumptions!$B$10),"loss") | D4: =IF((('Unit Economics'!$B$5*'Unit Economics'!$B$8*0.5*Assumptions!$B$11)-('Unit Economics'!$B$16*Assumptions!$B$11*0.5*(Assumptions!$B$6/100))-Assumptions!$B$9*'Unit Economics'!$B$13-Assumptions!$B$10)>0,'Unit Economics'!$B$13/(('Unit Economics'!$B$5*'Unit Economics'!$B$8*0.5*Assumptions!$B$11)-('Unit Economics'!$B$16*Assumptions!$B$11*0.5*(Assumptions!$B$6/100))-Assumptions!$B$9*'Unit Economics'!$B$13-Assumptions!$B$10),"loss") | E4: =IF((('Unit Economics'!$B$5*'Unit Economics'!$B$8*0.6*Assumptions!$B$11)-('Unit Economics'!$B$16*Assumptions!$B$11*0.6*(Assumptions!$B$6/100))-Assumptions!$B$9*'Unit Economics'!$B$13-Assumptions!$B$10)>0,'Unit Economics'!$B$13/(('Unit Economics'!$B$5*'Unit Economics'!$B$8*0.6*Assumptions!$B$11)-('Unit Economics'!$B$16*Assumptions!$B$11*0.6*(Assumptions!$B$6/100))-Assumptions!$B$9*'Unit Economics'!$B$13-Assumptions!$B$10),"loss") | F4: =IF((('Unit Economics'!$B$5*'Unit Economics'!$B$8*0.7*Assumptions!$B$11)-('Unit Economics'!$B$16*Assumptions!$B$11*0.7*(Assumptions!$B$6/100))-Assumptions!$B$9*'Unit Economics'!$B$13-Assumptions!$B$10)>0,'Unit Economics'!$B$13/(('Unit Economics'!$B$5*'Unit Economics'!$B$8*0.7*Assumptions!$B$11)-('Unit Economics'!$B$16*Assumptions!$B$11*0.7*(Assumptions!$B$6/100))-Assumptions!$B$9*'Unit Economics'!$B$13-Assumptions!$B$10),"loss") | G4: =IF((('Unit Economics'!$B$5*'Unit Economics'!$B$8*0.9*Assumptions!$B$11)-('Unit Economics'!$B$16*Assumptions!$B$11*0.9*(Assumptions!$B$6/100))-Assumptions!$B$9*'Unit Economics'!$B$13-Assumptions!$B$10)>0,'Unit Economics'!$B$13/(('Unit Economics'!$B$5*'Unit Economics'!$B$8*0.9*Assumptions!$B$11)-('Unit Economics'!$B$16*Assumptions!$B$11*0.9*(Assumptions!$B$6/100))-Assumptions!$B$9*'Unit Economics'!$B$13-Assumptions!$B$10),"loss")
A6: Occupancy is the number to MEASURE with one real box before scaling. Below ~50% the best card still misses a 2-year payback — Phase 2 token-serving is what lifts occupancy (and stabilises the heat).

Sheet Fleet Build
A1: Fleet Build — pools over 5 years (uses per-pool capex & net from Pool Model)
A3: Year | B3: Y1 | C3: Y2 | D3: Y3 | E3: Y4 | F3: Y5
A4: Pools added (input) | B4: 1 | C4: 3 | D4: 10 | E4: 25 | F4: 60
A5: Cumulative pools | B5: =B4 | C5: =B5+C4 | D5: =C5+D4 | E5: =D5+E4 | F5: =E5+F4
A6: Capex this year (£) | B6: =B4*'Pool Model'!$B$15 | C6: =C4*'Pool Model'!$B$15 | D6: =D4*'Pool Model'!$B$15 | E6: =E4*'Pool Model'!$B$15 | F6: =F4*'Pool Model'!$B$15
A7: Net profit (£/yr, cumulative) | B7: =B5*'Pool Model'!$B$16 | C7: =C5*'Pool Model'!$B$16 | D7: =D5*'Pool Model'!$B$16 | E7: =E5*'Pool Model'!$B$16 | F7: =F5*'Pool Model'!$B$16
A8: Annual cashflow (net − capex) | B8: =B7-B6 | C8: =C7-C6 | D8: =D7-D6 | E8: =E7-E6 | F8: =F7-F6
A9: Cumulative cashflow (£) | B9: =B8 | C9: =B9+C8 | D9: =C9+D8 | E9: =D9+E8 | F9: =E9+F8
A11: Capex is front-loaded — cumulative cash dips negative before it turns. Pace deployment to your cash.

Sheet Sources & Notes
A1: Sources & Notes
A3: REVENUE — host payout maths (the correction)
A4: Vast.ai host fee removed; renter premium added | B4: https://vast.ai/article/june-2024-product-update
A5: Vast.ai: live prices ~25% above host earnings | B5: https://vast.ai/article/how-much-money-can-you-earn-renting-out-your-gpu-on-vast-ai
A6: Vast.ai per-GPU rates | B6: https://vast.ai/pricing/gpu/RTX-4090
A7: Multi-provider rate tracker | B7: https://computeprices.com/providers/vast
A8: GPU prices (used/new, UK) | B8: https://bestvaluegpu.com/en-gb/
A9: Inference tok/s (Llama-3.1-8B) | B9: https://www.localscore.ai/model/1
A10: OpenRouter provider fee (0% from providers) | B10: https://openrouter.ai/announcements/simplifying-our-platform-fee
A11: ELECTRICITY
A12: Ofgem price cap (24.67p Q2 2026) | B12: https://www.ofgem.gov.uk/information-consumers/energy-advice-households/energy-price-cap-unit-rates-and-standing-charges
A13: Octopus Agile (~16p, time-shift) | B13: https://agileprices.co.uk/
A14: Pay-the-host mechanism (Heata) | B14: https://www.heata.co/hosts/sign-up
A15: MID submeter | B15: https://tewltd.co.uk/product/pjw-mid-approved-100a-din-rail-single-phase-kwh-meter-dr2100-2mod/
A16: CAPITAL (box components)
A17: Chassis / PSU | B17: https://www.scan.co.uk/
A18: GPU water blocks | B18: https://www.ekwb.com/shop/ek-quantum-vector-rtx-3080-3090-d-rgb-nickel-acetal
A19: Brazed-plate heat exchanger | B19: https://www.heat-exchangers.uk/pricelist/
A20: Pump / coolant | B20: https://www.watercoolinguk.co.uk/
A21: POOL + CHANNEL
A22: Indoor pool running cost | B22: https://www.originpools.co.uk/pools/indoor-pools/advice/cost-guides/how-much-does-it-cost-to-run-an-indoor-pool
A23: Pool heat pump COP / sizing | B23: https://heatpumps4pools.com/frequently-asked-questions-for-swimming-pool-heat-pumps/
A24: SPATA installer trade body | B24: https://www.spata.co.uk/
A25: Deep Green (pool incumbent) | B25: https://www.datacenterdynamics.com/en/news/uk-data-center-startup-offers-to-heat-britains-swimming-pools-with-waste-heat/
A27: HONEST HEADLINES
A28: • Host rate corrected: you receive Renter $/hr ÷ 1.25 ÷ 1.27 — earlier drafts ran ~25% hot.
A29: • Occupancy is the make-or-break and is UNMEASURED for home GPUs — measure it with one box.
A30: • VRAM gates demand: ≥24GB cards earn; sub-16GB sit idle and lose money after electricity.
A31: • Best for THIS business: RTX 4090 / 5090 (earn AND make real heat). 3090 pays back too slowly.
A32: • Heat recovery is REQUIRED — it is the host's free heat (the reason they host), and a cost to you.
A33: • Prices move fast — re-verify before committing capital.
