Workbook

Sheet £100k Answer
A1: £100k of your own money at a school — fastest payback
A2: £100k buys ~6 water-cooled boxes (36× RTX 4090, ~16kW). Chips die economically at ~3yr, so payback MUST beat 36 months. Yellow = edit the levers per row.
A4: Scenario | B4: Heat deal | C4: Util % | D4: Power p/kWh | E4: Heat sell p/kWh | F4: Net £/yr | G4: Payback (mo) | H4: ROC %/yr | I4: Profit window (mo) | J4: Verdict
A5: Free heat · no solar · SPOT | B5: free | C5: 0.55 | D5: 24 | E5: 0 | F5: =Assumptions!$B$7*(Assumptions!$B$6*Assumptions!$B$8*C5*Assumptions!$B$12 + Assumptions!$B$11*C5*Assumptions!$B$12*(E5/100) - Assumptions!$B$11*C5*Assumptions!$B$12*(D5/100) - Assumptions!$B$5*Assumptions!$B$9 - Assumptions!$B$10) | G5: =IF(F5>0,Assumptions!$B$4/F5*12,"never") | H5: =F5/Assumptions!$B$4 | I5: =IF(F5>0,MAX(0,36-Assumptions!$B$4/F5*12),0) | J5: =IF(G5="never","FAILS",IF(G5<=24,"FAST",IF(G5<36,"OK","FAILS")))
A6: Free heat · no solar · your token endpoint | B6: free | C6: 0.7 | D6: 24 | E6: 0 | F6: =Assumptions!$B$7*(Assumptions!$B$6*Assumptions!$B$8*C6*Assumptions!$B$12 + Assumptions!$B$11*C6*Assumptions!$B$12*(E6/100) - Assumptions!$B$11*C6*Assumptions!$B$12*(D6/100) - Assumptions!$B$5*Assumptions!$B$9 - Assumptions!$B$10) | G6: =IF(F6>0,Assumptions!$B$4/F6*12,"never") | H6: =F6/Assumptions!$B$4 | I6: =IF(F6>0,MAX(0,36-Assumptions!$B$4/F6*12),0) | J6: =IF(G6="never","FAILS",IF(G6<=24,"FAST",IF(G6<36,"OK","FAILS")))
A7: Free heat · no solar · CONTRACTED | B7: free | C7: 0.9 | D7: 24 | E7: 0 | F7: =Assumptions!$B$7*(Assumptions!$B$6*Assumptions!$B$8*C7*Assumptions!$B$12 + Assumptions!$B$11*C7*Assumptions!$B$12*(E7/100) - Assumptions!$B$11*C7*Assumptions!$B$12*(D7/100) - Assumptions!$B$5*Assumptions!$B$9 - Assumptions!$B$10) | G7: =IF(F7>0,Assumptions!$B$4/F7*12,"never") | H7: =F7/Assumptions!$B$4 | I7: =IF(F7>0,MAX(0,36-Assumptions!$B$4/F7*12),0) | J7: =IF(G7="never","FAILS",IF(G7<=24,"FAST",IF(G7<36,"OK","FAILS")))
A8: SELL heat (off-gas school) · grid · 70% | B8: sold | C8: 0.7 | D8: 24 | E8: 16 | F8: =Assumptions!$B$7*(Assumptions!$B$6*Assumptions!$B$8*C8*Assumptions!$B$12 + Assumptions!$B$11*C8*Assumptions!$B$12*(E8/100) - Assumptions!$B$11*C8*Assumptions!$B$12*(D8/100) - Assumptions!$B$5*Assumptions!$B$9 - Assumptions!$B$10) | G8: =IF(F8>0,Assumptions!$B$4/F8*12,"never") | H8: =F8/Assumptions!$B$4 | I8: =IF(F8>0,MAX(0,36-Assumptions!$B$4/F8*12),0) | J8: =IF(G8="never","FAILS",IF(G8<=24,"FAST",IF(G8<36,"OK","FAILS")))
A9: SELL heat (off-gas school) · grid · CONTRACTED | B9: sold | C9: 0.9 | D9: 24 | E9: 16 | F9: =Assumptions!$B$7*(Assumptions!$B$6*Assumptions!$B$8*C9*Assumptions!$B$12 + Assumptions!$B$11*C9*Assumptions!$B$12*(E9/100) - Assumptions!$B$11*C9*Assumptions!$B$12*(D9/100) - Assumptions!$B$5*Assumptions!$B$9 - Assumptions!$B$10) | G9: =IF(F9>0,Assumptions!$B$4/F9*12,"never") | H9: =F9/Assumptions!$B$4 | I9: =IF(F9>0,MAX(0,36-Assumptions!$B$4/F9*12),0) | J9: =IF(G9="never","FAILS",IF(G9<=24,"FAST",IF(G9<36,"OK","FAILS")))
A10: Free heat · SOLAR school · CONTRACTED | B10: free | C10: 0.9 | D10: 12 | E10: 0 | F10: =Assumptions!$B$7*(Assumptions!$B$6*Assumptions!$B$8*C10*Assumptions!$B$12 + Assumptions!$B$11*C10*Assumptions!$B$12*(E10/100) - Assumptions!$B$11*C10*Assumptions!$B$12*(D10/100) - Assumptions!$B$5*Assumptions!$B$9 - Assumptions!$B$10) | G10: =IF(F10>0,Assumptions!$B$4/F10*12,"never") | H10: =F10/Assumptions!$B$4 | I10: =IF(F10>0,MAX(0,36-Assumptions!$B$4/F10*12),0) | J10: =IF(G10="never","FAILS",IF(G10<=24,"FAST",IF(G10<36,"OK","FAILS")))
A11: SELL heat + SOLAR · 70% (realistic best) | B11: sold | C11: 0.7 | D11: 12 | E11: 16 | F11: =Assumptions!$B$7*(Assumptions!$B$6*Assumptions!$B$8*C11*Assumptions!$B$12 + Assumptions!$B$11*C11*Assumptions!$B$12*(E11/100) - Assumptions!$B$11*C11*Assumptions!$B$12*(D11/100) - Assumptions!$B$5*Assumptions!$B$9 - Assumptions!$B$10) | G11: =IF(F11>0,Assumptions!$B$4/F11*12,"never") | H11: =F11/Assumptions!$B$4 | I11: =IF(F11>0,MAX(0,36-Assumptions!$B$4/F11*12),0) | J11: =IF(G11="never","FAILS",IF(G11<=24,"FAST",IF(G11<36,"OK","FAILS")))
A12: SELL heat + SOLAR · CONTRACTED (ceiling) | B12: sold | C12: 0.9 | D12: 12 | E12: 16 | F12: =Assumptions!$B$7*(Assumptions!$B$6*Assumptions!$B$8*C12*Assumptions!$B$12 + Assumptions!$B$11*C12*Assumptions!$B$12*(E12/100) - Assumptions!$B$11*C12*Assumptions!$B$12*(D12/100) - Assumptions!$B$5*Assumptions!$B$9 - Assumptions!$B$10) | G12: =IF(F12>0,Assumptions!$B$4/F12*12,"never") | H12: =F12/Assumptions!$B$4 | I12: =IF(F12>0,MAX(0,36-Assumptions!$B$4/F12*12),0) | J12: =IF(G12="never","FAILS",IF(G12<=24,"FAST",IF(G12<36,"OK","FAILS")))
A14: THE ANSWER TO 'FREE HEAT, NO SOLAR': it wins you the SITE (free = no procurement, fast yes) but on grid power it needs CONTRACTED demand just to reach ~34mo — past the 3-yr chip cliff — and on spot it's 5+ years. Free heat opens the door; it does not pay the bills.
A15: FASTEST RETURN: a school that is OFF the gas grid (oil/electric heat worth ~20–25p/kWh, so SELL it at a discount) AND has solar — payback ~17–22 months, ~£55–71k/yr on your £100k. The demand lever (your own token endpoint or one anchor customer for 36 GPUs) is the bit you must secure; at this small scale it's tractable, unlike a 4MW site.

Sheet Assumptions
A1: Assumptions (edit yellow)
A4: Your capital £ | B4: 100000
A5: Box cost £ (6× RTX 4090, water-cooled, audited) | B5: 15200
A6: GPUs per box | B6: 6
A7: Boxes (= capital ÷ box cost) | B7: =ROUNDDOWN(B4/B5,0)
A8: Host £/hr per GPU (compute rate, contracted) | B8: 0.252 | C8: audited typical host rate; spot is similar £/hr but lower util
A9: Maintenance %/yr | B9: 0.05
A10: Other opex £/box/yr | B10: 150
A11: Box power (kW) | B11: 2.7
A12: Hours/yr | B12: 8760
A14: THE LEVER MENU (set per scenario on the Answer tab):
A15: Util: spot ~55% · your token endpoint ~70% · contracted ~90%
A16: Power: school grid ~24p · school SOLAR (behind-meter) ~12p
A17: Heat: FREE (0p, wins the site) · SOLD to an off-gas school (oil/electric heat worth 20–25p → sell ~16p)
A18: Heat sold p/kWh is YOUR second revenue line; only worthwhile where the school's heat is expensive (off gas grid)

Sheet Notes
A1: Notes — the trade-offs behind the numbers
A3: 1. FREE HEAT vs SOLD HEAT is a SPEED-vs-MONEY trade. Free heat = no procurement, a fast 'yes', fast deployment of your £100k → the payback clock starts sooner. Sold heat = a heat-supply contract (procurement friction, schools are slow) but a second revenue line of ~£3.4k/box/yr at an off-gas school. Lead with free to win the door; switch to discounted heat where the heat is expensive.
A4: 2. WHERE HEAT IS WORTH SELLING: gas-heated schools displace heat worth only ~6p/kWh — selling it adds little. OFF-GAS-GRID schools (rural, oil/LPG/electric) displace 8–25p/kWh — there the heat is a real second revenue stream. Bonus: rural off-gas schools are also the ones most likely to have roof/land for solar. That convergence (valuable heat + solar) is your best first site.
A5: 3. THE DEMAND LEVER IS STILL THE BOTTLENECK — but tractable at this scale. 36 GPUs is a small endpoint you could plausibly fill via your own OpenRouter token-serving or one anchor customer (~£30–50k/mo deal). 90% 'contracted' is the optimistic ceiling; 70% (your-own-endpoint, ramping) is the realistic planning number — that's why both are shown.
A6: 4. CHIP LIFE is the hard ceiling. A GPU's rental rate collapses ~80–95% over 5–6 years (V100 now $0.02/hr). Treat 36 months as the must-beat line; anything over ~30mo leaves almost no profit window before you re-capex the chips.
A7: 5. WHAT £100k REALLY BUYS YOU: even in the best case it's ~£55–71k/yr — a good return on £100k, but a SMALL business in absolute terms. Its bigger value is PROOF: one site that pays back in <2 years validates a repeatable unit you can then scale or raise against. Treat the first £100k as buying both cash AND de-risking evidence.
