Workbook

Sheet Models & Evidence
A1: How it could actually work — 4 levers, each proven by a real operator
A2: The spot-rental floor (buy GPUs, rent on Vast, give heat free) does NOT pay back in 1–2 yrs. Every PROFITABLE operator pulls these levers instead. See the 'Scenarios' tab for the numbers, 'Real Businesses' for the evidence.
A4: LEVER | B4: What it does | C4: Why it works | D4: Proven by | E4: UK route for you
A5: 1. CHEAP / STRANDED POWER | B5: Run on behind-the-meter renewable power at near-zero marginal cost instead of 25p grid | C5: Electricity is 30–50% of opex at high utilisation. Crusoe/Soluna pay ~3p vs 25p — the single biggest lever | D5: Crusoe (stranded gas, $998M rev), Soluna (curtailed wind ~3p), IREN, EcoDataCenter (Swedish hydro) | E5: Your friend's 400 SOLAR SCHOOLS (behind-meter summer surplus ~0–12p); or curtailed Scottish wind (~900 GWh/yr wasted)
A6: 2. CONTRACTED / OWN DEMAND | B6: Sell to a committed customer or your own token endpoint — NOT the spot market | C6: Lifts utilisation from ~55% (spot) to 85–95%, and stabilises the rate. Spot occupancy is the killer uncertainty | D6: Crusoe (Oracle 15-yr lease), IREN (Microsoft $9.7bn), Soluna (single-tenant LT), Qarnot (enterprise HPC) | E6: Phase 2 token-serving (OpenRouter provider), or one anchor compute customer before you scale
A7: 3. GRID SERVICES | B7: Get PAID by the grid to be a flexible load that can curtail on demand | C7: A second revenue line for hardware you already own; material at MW scale | D7: Soluna (ERCOT demand response), Lancium (CLR ancillary services + Smart Response licensing) | E7: UK Demand Side Response / Balancing Mechanism / Capacity Market (~£40–150/kW/yr) via a licensed aggregator
A8: 4. HEAT FOR SITING | B8: Give heat free to a host who displaces expensive heating; you get free site + free cooling | C8: Eliminates ~30–40% cooling opex AND buys zero-rent siting. Heat SALE to a utility is tiny (£3–7/MWh); heat DISPLACEMENT to the host is worth 4p (gas) to 25p (electric) | D8: Deep Green (pools, £200m Octopus), Qarnot (buildings), Heata (homes), MintGreen (sells heat to utility) | E8: Pools (Deep Green's space — avoid), care homes / laundries (electric heat = 25p displaced = valuable), schools
A9: THE SYNTHESIS | B9: Stack levers 1+2 (+3,+4). That is what every profitable operator does. | C9: Spot+grid floor = ~58 mo. Cheap power + contracted demand = ~17–20 mo. Heat & grid services trim further. | D9: Crusoe / Soluna / EcoDataCenter all = cheap power + contracted demand. None runs spot-rental. | E9: Schools (cheap solar power + heat siting) + your own contracted compute = the viable UK business

Sheet Assumptions
A1: Assumptions — the common hardware unit (edit yellow)
A2: One deployment unit = a 6× RTX 4090 box (audited capex from the floor model). Switch GPU/capex here; the Scenarios tab recomputes.
A4: HARDWARE UNIT (audited 7 Jun 2026)
A5: GPUs per box | B5: 6
A6: Capex per box, fully loaded £ | B6: 15200 | C6: 6× RTX 4090 @ £1,843 + box + heat recovery + install (see floor-model BoM)
A7: Power draw per box (kW) | B7: 2.7
A8: Maintenance (% of capex / yr) | B8: 0.05
A9: Other opex (£/box/yr) | B9: 150
A10: Hours per year | B10: 8760
A11: tok/s per GPU (Llama-3.1-8B, for token mode) | B11: 120
A14: THE LEVER MENU (what each scenario draws from)
A15: POWER (p/kWh) | B15: grid cap ~25 · cheap PPA ~8 · curtailed behind-meter ~3 · free solar surplus ~0
A16: DEMAND → utilisation | B16: spot ~55% · token (own endpoint) ~85% · contracted ~90%
A17: RATE | B17: spot rental host £0.25/hr · token £0.55/M ≈ £0.24/hr-equiv (120 tok/s)
A18: GRID SERVICES | B18: UK DSR / Balancing Mechanism / Capacity Market ~£40–150/kW/yr (bigger at MW scale)
A19: HEAT (siting, not your revenue) | B19: displaced value to host: gas ~4p · pool heat-pump ~5.5p · electric ~25p /kWh
A22: Heat note: SELLING heat to a district network is tiny (£3–7/MWh). Heat's real value is DISPLACING the host's heating (gas 4p, electric 25p) — given free, it buys the cheap-power site + free cooling. That's why it's a siting lever, not a revenue line.

Sheet Scenarios
A1: Scenarios — same box, different business model (each grounded in a real operator)
A2: Yellow = the levers (edit them). Net/Payback/ROC compute live off the Assumptions box. The story: spot+grid = floor; cheap power + contracted demand = viable.
A4: Scenario | B4: Based on | C4: Power p/kWh | D4: Util % | E4: Eff £/hr/GPU | F4: Grid svc £/yr | G4: Software £/yr | H4: Revenue £/yr | I4: Power £/yr | J4: NET £/yr | K4: Payback (mo) | L4: ROC %/yr | M4: Verdict
A5: Spot floor (the trap) | B5: Vast.ai spot | C5: 25 | D5: 0.55 | E5: 0.252 | F5: 0 | G5: 0 | H5: =Assumptions!$B$5*E5*D5*Assumptions!$B$10 | I5: =Assumptions!$B$7*Assumptions!$B$10*D5*(C5/100) | J5: =H5+F5-I5-G5-Assumptions!$B$6*Assumptions!$B$8-Assumptions!$B$9 | K5: =IF(J5>0,Assumptions!$B$6/J5*12,"never") | L5: =J5/Assumptions!$B$6 | M5: =IF(K5<=24,"viable",IF(K5<=36,"marginal","fails"))
A6: Token, GRID power | B6: Qarnot w/o cheap power | C6: 25 | D6: 0.85 | E6: 0.238 | F6: 0 | G6: 1000 | H6: =Assumptions!$B$5*E6*D6*Assumptions!$B$10 | I6: =Assumptions!$B$7*Assumptions!$B$10*D6*(C6/100) | J6: =H6+F6-I6-G6-Assumptions!$B$6*Assumptions!$B$8-Assumptions!$B$9 | K6: =IF(J6>0,Assumptions!$B$6/J6*12,"never") | L6: =J6/Assumptions!$B$6 | M6: =IF(K6<=24,"viable",IF(K6<=36,"marginal","fails"))
A7: Token, CHEAP power | B7: Qarnot + Crusoe | C7: 8 | D7: 0.85 | E7: 0.238 | F7: 0 | G7: 1000 | H7: =Assumptions!$B$5*E7*D7*Assumptions!$B$10 | I7: =Assumptions!$B$7*Assumptions!$B$10*D7*(C7/100) | J7: =H7+F7-I7-G7-Assumptions!$B$6*Assumptions!$B$8-Assumptions!$B$9 | K7: =IF(J7>0,Assumptions!$B$6/J7*12,"never") | L7: =J7/Assumptions!$B$6 | M7: =IF(K7<=24,"viable",IF(K7<=36,"marginal","fails"))
A8: Contracted + host power | B8: Deep Green (UK) | C8: 8 | D8: 0.9 | E8: 0.252 | F8: 0 | G8: 0 | H8: =Assumptions!$B$5*E8*D8*Assumptions!$B$10 | I8: =Assumptions!$B$7*Assumptions!$B$10*D8*(C8/100) | J8: =H8+F8-I8-G8-Assumptions!$B$6*Assumptions!$B$8-Assumptions!$B$9 | K8: =IF(J8>0,Assumptions!$B$6/J8*12,"never") | L8: =J8/Assumptions!$B$6 | M8: =IF(K8<=24,"viable",IF(K8<=36,"marginal","fails"))
A9: Contracted + curtailed power | B9: Crusoe / IREN (UK) | C9: 3 | D9: 0.9 | E9: 0.252 | F9: 0 | G9: 0 | H9: =Assumptions!$B$5*E9*D9*Assumptions!$B$10 | I9: =Assumptions!$B$7*Assumptions!$B$10*D9*(C9/100) | J9: =H9+F9-I9-G9-Assumptions!$B$6*Assumptions!$B$8-Assumptions!$B$9 | K9: =IF(J9>0,Assumptions!$B$6/J9*12,"never") | L9: =J9/Assumptions!$B$6 | M9: =IF(K9<=24,"viable",IF(K9<=36,"marginal","fails"))
A10: Contracted + curtailed + grid svc | B10: Soluna / Lancium (UK) | C10: 3 | D10: 0.9 | E10: 0.252 | F10: 162 | G10: 0 | H10: =Assumptions!$B$5*E10*D10*Assumptions!$B$10 | I10: =Assumptions!$B$7*Assumptions!$B$10*D10*(C10/100) | J10: =H10+F10-I10-G10-Assumptions!$B$6*Assumptions!$B$8-Assumptions!$B$9 | K10: =IF(J10>0,Assumptions!$B$6/J10*12,"never") | L10: =J10/Assumptions!$B$6 | M10: =IF(K10<=24,"viable",IF(K10<=36,"marginal","fails"))
A12: READ IT TOP-TO-BOTTOM: the spot floor fails (~58 mo). Token only works with cheap power. The two viable rows are CONTRACTED DEMAND + CHEAP POWER (~17–20 mo) — exactly what Crusoe, Soluna, IREN and EcoDataCenter all do. Heat buys the cheap-power site; grid services + heat trim the rest.
A13: Honest caveat: the viable rows REQUIRE you to secure (a) cheap behind-the-meter power AND (b) contracted/own high-utilisation demand. Neither is free. The schools+solar channel gives (a); Phase-2 token-serving or one anchor customer gives (b). Without both, you're on the floor.

Sheet Real Businesses
A1: The evidence — global operators (researched 7 Jun 2026)
A2: Funding ≠ profitable. 'Proven?' flags genuine revenue vs VC bet. The heat pure-plays validate the concept; the profitable ones run cheap power + contracted demand.
A4: Company | B4: Country | C4: Type | D4: Power | E4: Demand | F4: Heat | G4: Funding / scale | H4: Proven?
A5: Crusoe | B5: USA | C5: Asset-heavy | D5: Stranded gas / curtailed renewables (BTM) | E5: Hyperscale lease (Oracle 15yr) + GPUaaS | F5: none | G5: $3.9bn raised; ~$998M rev 2025 | H5: Yes — biggest credible build; pre-profit
A6: IREN | B6: Australia/USA | C6: Asset-heavy | D6: Renewables PPA + energy trading | E6: Microsoft $9.7bn contract | F6: none | G6: Nasdaq; $240M Q1; ARR target $4.4bn | H6: Yes — profitable (with revaluation caveats)
A7: Soluna | B7: USA | C7: Asset-heavy | D7: Curtailed wind/solar (~3p, BTM) | E7: Single-tenant LT hosting + grid demand-response | F7: none | G7: Nasdaq; $29.7M rev 2025 | H7: No — −$57M; but hosting 40–59% gross margin
A8: EcoDataCenter | B8: Sweden | C8: Asset-heavy | D8: Swedish hydro grid | E8: CoreWeave AI anchor (wholesale) | F8: SOLD to utility (pellet plant + district) | G8: €1.8bn financed (Areim) | H8: Yes — most proven; heat genuinely sold
A9: atNorth / Verne / Borealis | B9: Iceland/Nordics | C9: Asset-heavy | D9: Geothermal + hydro (~3–5¢, PPA) | E9: Enterprise AI/HPC colocation (LT) | F9: pilot only | G9: PE / debt-funded (£100M+ each) | H9: Yes — institutional infra; heat nascent
A10: Lancium | B10: USA | C10: Asset-heavy | D10: Curtailed West-Texas wind (BTM) | E10: Anchor tenants + ERCOT ancillary + software licensing | F10: none | G10: Private; Crusoe cross-licence | H10: Proven but opaque
A11: Salad | B11: USA | C11: Asset-LIGHT platform | D11: Consumer grid (hosts pay) | E11: SME spot marketplace | F11: none | G11: $27.5M raised; $10.4M ARR | H11: Yes — growing, pre-profit. NO hardware
A12: Vast.ai | B12: USA | C12: Asset-LIGHT platform | D12: Hosts pay own (70% pros) | E12: Developer spot; 25–30% commission | F12: none | G12: Bootstrapped; ~$2.2M ARR | H12: Likely breakeven, lean. NO hardware
A13: Akash | B13: USA | C13: Asset-LIGHT platform | D13: Provider pays own | E13: Spot; 20% take rate | F13: none | G13: On-chain; ~$0.5M/qtr, declining | H13: Real but tiny + decelerating
A14: Deep Green | B14: UK | C14: Heat pure-play | D14: Grid (free cooling from pool) | E14: Enterprise AI/ML/rendering | F14: FREE to pool (siting) | G14: £200m Octopus; 1 live site | H14: Concept proven; not yet profitable/scaled
A15: Qarnot | B15: France | C15: Heat pure-play | D15: Grid at each building | E15: Enterprise HPC (aerospace, AI) | F15: reduced-cost to building; util offtake (IT) | G15: ~€55M; ~1MW, 30 sites, 10+ yrs | H15: Most proven distributed-heat; profit unclear
... A20: Infomaniak | B20: Switzerland | C20: Cloud + heat | D20: Swiss grid (hydro) | E20: own cloud customers | F20: SOLD to utility at cost (heat pumps to 85°C) | G20: Cooperative, no VC; CHF12m DC | H20: Yes — but heat is cost-neutral
A22: THE PATTERN: every PROFITABLE asset-heavy operator = cheap/stranded power + contracted demand. The asset-LIGHT platforms make money with NO hardware (a spread on sunk-cost gamers' GPUs). The heat pure-plays prove the concept but none is profitable yet. Your edge = schools' cheap solar power + heat siting + your own contracted demand.

Sheet Sources
A1: Sources (researched 7 Jun 2026)
A3: PROFITABLE ASSET-HEAVY (cheap power + contracted demand)
A4: Crusoe — Contrary Research deep dive | B4: https://research.contrary.com/company/crusoe
A5: Soluna 2025 annual results (curtailed-wind hosting + demand response) | B5: https://www.solunacomputing.com/news/2025-results/
A6: IREN — Microsoft $9.7bn AI cloud deal | B6: https://bravenewcoin.com/insights/bitcoin-miner-iren-lands-9-7-billion-microsoft-deal-for-ai-infrastructure
A7: EcoDataCenter — €600m raise + CoreWeave + heat-to-pellet | B7: https://ecodatacenter.tech/press/ecodatacenter-raises-an-additional-eur-600-million-3402903
A8: Lancium — ERCOT Controllable Load Resource (grid services) | B8: https://www.prnewswire.com/news-releases/lanciums-fort-stockton-facility-qualifies-as-ercot-controllable-load-resource-301666372.html
A9: ASSET-LIGHT PLATFORMS (no hardware, take a spread)
A10: Salad — host earnings (sunk-cost gamer GPUs) | B10: https://community.salad.com/sell-gpu-power/
A11: Salad — revenue/ARR | B11: https://getlatka.com/companies/salad-technologies
A12: Vast.ai — 25% renter premium, host keeps ~80% | B12: https://vast.ai/article/how-much-money-can-you-earn-renting-out-your-gpu-on-vast-ai
A13: Akash — Messari state report (20% take, declining) | B13: https://messari.io/report/state-of-akash-q3-2025
A14: HEAT PURE-PLAYS (concept proven, not yet profitable)
A15: Deep Green — Octopus £200m, pools | B15: https://thenextweb.com/news/deep-green-octopus-energy-swimming-pools-data-centre
A16: Qarnot — distributed building HPC + heat | B16: https://www.datacenterdynamics.com/en/news/hpc-cloud-provider-qarnot-gets-funding-from-european-innovation-council/
A17: Heata — British Gas trial | B17: https://www.centrica.com/media-centre/news/2025/british-gas-partners-with-heata-on-trial-to-reuse-waste-heat-from-data-processing/
A18: MintGreen — sells heat to district utility | B18: https://www.districtenergy.org/blogs/district-energy/2024/04/16/how-a-startup-is-supplying-a-whole-city-with-heat
A19: Stockholm Exergi — Open District Heating (buys heat at avoided-cost) | B19: https://stockholmdataparks.com/
A20: Green Mountain — heat to lobster/trout farms | B20: https://greenmountain.no/data-center-heat-reuse/
A21: Infomaniak — 100% heat recovery to Geneva district | B21: https://www.globenewswire.com/news-releases/2025/01/28/3016567/0/en/Innovation-Infomaniak-inaugurates-a-data-center-that-recycles-100-of-its-energy-and-will-heat-6-000-households-a-year-for-at-least-20-years.html
A22: LEVER EVIDENCE
A23: UK wind curtailment (~900 GWh/yr wasted Scotland) | B23: https://www.carbontracker.org/
A24: UK Demand Side Response / Balancing Mechanism (grid services) | B24: https://www.nationalgrideso.com/industry-information/balancing-services
A25: DC waste-heat unit economics (€3–7/MWh sale; gas baseline €35–55/MWh) | B25: https://energy-solutions.co/articles/sub/data-center-waste-heat-district-heating
