Workbook

Sheet Assumptions
A1: Poultry plant-room — assumptions (edit yellow)
A2: A broiler house ≈330 MWh/yr heat. Compute sits in an external plant room (like your biomass boiler), feeds the wet loop; the existing boiler peaks, a dry-cooler dumps excess. Big roof → solar.
A4: House heat demand (MWh/yr) | B4: 330
A5: Compute boxes (£100k ≈ 6) | B5: 6
A6: kW per box | B6: 2.7
A7: Utilisation (compute earning) | B7: 0.8
A8: GPUs per box | B8: 6
A9: Host £/hr per GPU | B9: 0.252
A10: Roof solar (kWp) — sized to compute | B10: 40 | C10: roof can hold ~300 kWp — rest powers the farm/exports
A11: Displaced fuel price (p/kWh) | B11: 12 | C11: LPG ~12 · oil ~8.5 · biomass ~5 · electric ~25
A12: Heat discount you give (charge this × fuel) | B12: 0.5
A13: Grid day/peak (p/kWh) | B13: 25
A14: Grid night/off-peak (p/kWh) | B14: 13
A15: Solar LCOE (p/kWh) | B15: 4
A16: Heat-use loss (cleanout gaps) | B16: 0.9
A17: Maintenance (% capex/yr) | B17: 0.05
A18: Box cost £ | B18: 15200
A19: Opex £/box/yr | B19: 150
A20: Dry-cooler (heat dump) capex £ | B20: 4000
A21: Daylight window (h) | B21: 12

Sheet Monthly
A1: The seasonal picture — heat demand vs compute heat vs solar (live)
A2: Winter: house wants lots of heat, little solar (power dear) — heat fully used. Summer: little heat wanted, lots of solar (power cheap) — some heat dumped. The two hedge.
A4: Month | B4: Days | C4: PSH | D4: House demand | E4: Compute heat | F4: Heat used | G4: Heat dumped | H4: Solar gen | I4: Solar used | J4: Grid day | K4: Grid night | L4: Power £ | M4: Heat rev £
A5: Jan | B5: 31 | C5: 0.74 | D5: =Assumptions!$B$4*1000*0.125 | E5: =Assumptions!$B$5*Assumptions!$B$6*Assumptions!$B$7*B5*24 | F5: =MIN(D5,E5)*Assumptions!$B$16 | G5: =E5-F5 | H5: =Assumptions!$B$10*C5*B5 | I5: =MIN(H5,Assumptions!$B$5*Assumptions!$B$6*Assumptions!$B$7*Assumptions!$B$21*B5) | J5: =Assumptions!$B$5*Assumptions!$B$6*Assumptions!$B$7*Assumptions!$B$21*B5-I5 | K5: =Assumptions!$B$5*Assumptions!$B$6*Assumptions!$B$7*(24-Assumptions!$B$21)*B5 | L5: =(I5*Assumptions!$B$15+J5*Assumptions!$B$13+K5*Assumptions!$B$14)/100 | M5: =F5*Assumptions!$B$11*Assumptions!$B$12/100
A6: Feb | B6: 28 | C6: 1.36 | D6: =Assumptions!$B$4*1000*0.115 | E6: =Assumptions!$B$5*Assumptions!$B$6*Assumptions!$B$7*B6*24 | F6: =MIN(D6,E6)*Assumptions!$B$16 | G6: =E6-F6 | H6: =Assumptions!$B$10*C6*B6 | I6: =MIN(H6,Assumptions!$B$5*Assumptions!$B$6*Assumptions!$B$7*Assumptions!$B$21*B6) | J6: =Assumptions!$B$5*Assumptions!$B$6*Assumptions!$B$7*Assumptions!$B$21*B6-I6 | K6: =Assumptions!$B$5*Assumptions!$B$6*Assumptions!$B$7*(24-Assumptions!$B$21)*B6 | L6: =(I6*Assumptions!$B$15+J6*Assumptions!$B$13+K6*Assumptions!$B$14)/100 | M6: =F6*Assumptions!$B$11*Assumptions!$B$12/100
A7: Mar | B7: 31 | C7: 2.31 | D7: =Assumptions!$B$4*1000*0.1 | E7: =Assumptions!$B$5*Assumptions!$B$6*Assumptions!$B$7*B7*24 | F7: =MIN(D7,E7)*Assumptions!$B$16 | G7: =E7-F7 | H7: =Assumptions!$B$10*C7*B7 | I7: =MIN(H7,Assumptions!$B$5*Assumptions!$B$6*Assumptions!$B$7*Assumptions!$B$21*B7) | J7: =Assumptions!$B$5*Assumptions!$B$6*Assumptions!$B$7*Assumptions!$B$21*B7-I7 | K7: =Assumptions!$B$5*Assumptions!$B$6*Assumptions!$B$7*(24-Assumptions!$B$21)*B7 | L7: =(I7*Assumptions!$B$15+J7*Assumptions!$B$13+K7*Assumptions!$B$14)/100 | M7: =F7*Assumptions!$B$11*Assumptions!$B$12/100
A8: Apr | B8: 30 | C8: 3.42 | D8: =Assumptions!$B$4*1000*0.075 | E8: =Assumptions!$B$5*Assumptions!$B$6*Assumptions!$B$7*B8*24 | F8: =MIN(D8,E8)*Assumptions!$B$16 | G8: =E8-F8 | H8: =Assumptions!$B$10*C8*B8 | I8: =MIN(H8,Assumptions!$B$5*Assumptions!$B$6*Assumptions!$B$7*Assumptions!$B$21*B8) | J8: =Assumptions!$B$5*Assumptions!$B$6*Assumptions!$B$7*Assumptions!$B$21*B8-I8 | K8: =Assumptions!$B$5*Assumptions!$B$6*Assumptions!$B$7*(24-Assumptions!$B$21)*B8 | L8: =(I8*Assumptions!$B$15+J8*Assumptions!$B$13+K8*Assumptions!$B$14)/100 | M8: =F8*Assumptions!$B$11*Assumptions!$B$12/100
A9: May | B9: 31 | C9: 4.38 | D9: =Assumptions!$B$4*1000*0.055 | E9: =Assumptions!$B$5*Assumptions!$B$6*Assumptions!$B$7*B9*24 | F9: =MIN(D9,E9)*Assumptions!$B$16 | G9: =E9-F9 | H9: =Assumptions!$B$10*C9*B9 | I9: =MIN(H9,Assumptions!$B$5*Assumptions!$B$6*Assumptions!$B$7*Assumptions!$B$21*B9) | J9: =Assumptions!$B$5*Assumptions!$B$6*Assumptions!$B$7*Assumptions!$B$21*B9-I9 | K9: =Assumptions!$B$5*Assumptions!$B$6*Assumptions!$B$7*(24-Assumptions!$B$21)*B9 | L9: =(I9*Assumptions!$B$15+J9*Assumptions!$B$13+K9*Assumptions!$B$14)/100 | M9: =F9*Assumptions!$B$11*Assumptions!$B$12/100
A10: Jun | B10: 30 | C10: 4.5 | D10: =Assumptions!$B$4*1000*0.045 | E10: =Assumptions!$B$5*Assumptions!$B$6*Assumptions!$B$7*B10*24 | F10: =MIN(D10,E10)*Assumptions!$B$16 | G10: =E10-F10 | H10: =Assumptions!$B$10*C10*B10 | I10: =MIN(H10,Assumptions!$B$5*Assumptions!$B$6*Assumptions!$B$7*Assumptions!$B$21*B10) | J10: =Assumptions!$B$5*Assumptions!$B$6*Assumptions!$B$7*Assumptions!$B$21*B10-I10 | K10: =Assumptions!$B$5*Assumptions!$B$6*Assumptions!$B$7*(24-Assumptions!$B$21)*B10 | L10: =(I10*Assumptions!$B$15+J10*Assumptions!$B$13+K10*Assumptions!$B$14)/100 | M10: =F10*Assumptions!$B$11*Assumptions!$B$12/100
A11: Jul | B11: 31 | C11: 4.35 | D11: =Assumptions!$B$4*1000*0.045 | E11: =Assumptions!$B$5*Assumptions!$B$6*Assumptions!$B$7*B11*24 | F11: =MIN(D11,E11)*Assumptions!$B$16 | G11: =E11-F11 | H11: =Assumptions!$B$10*C11*B11 | I11: =MIN(H11,Assumptions!$B$5*Assumptions!$B$6*Assumptions!$B$7*Assumptions!$B$21*B11) | J11: =Assumptions!$B$5*Assumptions!$B$6*Assumptions!$B$7*Assumptions!$B$21*B11-I11 | K11: =Assumptions!$B$5*Assumptions!$B$6*Assumptions!$B$7*(24-Assumptions!$B$21)*B11 | L11: =(I11*Assumptions!$B$15+J11*Assumptions!$B$13+K11*Assumptions!$B$14)/100 | M11: =F11*Assumptions!$B$11*Assumptions!$B$12/100
A12: Aug | B12: 31 | C12: 3.78 | D12: =Assumptions!$B$4*1000*0.045 | E12: =Assumptions!$B$5*Assumptions!$B$6*Assumptions!$B$7*B12*24 | F12: =MIN(D12,E12)*Assumptions!$B$16 | G12: =E12-F12 | H12: =Assumptions!$B$10*C12*B12 | I12: =MIN(H12,Assumptions!$B$5*Assumptions!$B$6*Assumptions!$B$7*Assumptions!$B$21*B12) | J12: =Assumptions!$B$5*Assumptions!$B$6*Assumptions!$B$7*Assumptions!$B$21*B12-I12 | K12: =Assumptions!$B$5*Assumptions!$B$6*Assumptions!$B$7*(24-Assumptions!$B$21)*B12 | L12: =(I12*Assumptions!$B$15+J12*Assumptions!$B$13+K12*Assumptions!$B$14)/100 | M12: =F12*Assumptions!$B$11*Assumptions!$B$12/100
A13: Sep | B13: 30 | C13: 2.82 | D13: =Assumptions!$B$4*1000*0.065 | E13: =Assumptions!$B$5*Assumptions!$B$6*Assumptions!$B$7*B13*24 | F13: =MIN(D13,E13)*Assumptions!$B$16 | G13: =E13-F13 | H13: =Assumptions!$B$10*C13*B13 | I13: =MIN(H13,Assumptions!$B$5*Assumptions!$B$6*Assumptions!$B$7*Assumptions!$B$21*B13) | J13: =Assumptions!$B$5*Assumptions!$B$6*Assumptions!$B$7*Assumptions!$B$21*B13-I13 | K13: =Assumptions!$B$5*Assumptions!$B$6*Assumptions!$B$7*(24-Assumptions!$B$21)*B13 | L13: =(I13*Assumptions!$B$15+J13*Assumptions!$B$13+K13*Assumptions!$B$14)/100 | M13: =F13*Assumptions!$B$11*Assumptions!$B$12/100
A14: Oct | B14: 31 | C14: 1.61 | D14: =Assumptions!$B$4*1000*0.085 | E14: =Assumptions!$B$5*Assumptions!$B$6*Assumptions!$B$7*B14*24 | F14: =MIN(D14,E14)*Assumptions!$B$16 | G14: =E14-F14 | H14: =Assumptions!$B$10*C14*B14 | I14: =MIN(H14,Assumptions!$B$5*Assumptions!$B$6*Assumptions!$B$7*Assumptions!$B$21*B14) | J14: =Assumptions!$B$5*Assumptions!$B$6*Assumptions!$B$7*Assumptions!$B$21*B14-I14 | K14: =Assumptions!$B$5*Assumptions!$B$6*Assumptions!$B$7*(24-Assumptions!$B$21)*B14 | L14: =(I14*Assumptions!$B$15+J14*Assumptions!$B$13+K14*Assumptions!$B$14)/100 | M14: =F14*Assumptions!$B$11*Assumptions!$B$12/100
A15: Nov | B15: 30 | C15: 0.86 | D15: =Assumptions!$B$4*1000*0.105 | E15: =Assumptions!$B$5*Assumptions!$B$6*Assumptions!$B$7*B15*24 | F15: =MIN(D15,E15)*Assumptions!$B$16 | G15: =E15-F15 | H15: =Assumptions!$B$10*C15*B15 | I15: =MIN(H15,Assumptions!$B$5*Assumptions!$B$6*Assumptions!$B$7*Assumptions!$B$21*B15) | J15: =Assumptions!$B$5*Assumptions!$B$6*Assumptions!$B$7*Assumptions!$B$21*B15-I15 | K15: =Assumptions!$B$5*Assumptions!$B$6*Assumptions!$B$7*(24-Assumptions!$B$21)*B15 | L15: =(I15*Assumptions!$B$15+J15*Assumptions!$B$13+K15*Assumptions!$B$14)/100 | M15: =F15*Assumptions!$B$11*Assumptions!$B$12/100
A16: Dec | B16: 31 | C16: 0.6 | D16: =Assumptions!$B$4*1000*0.14 | E16: =Assumptions!$B$5*Assumptions!$B$6*Assumptions!$B$7*B16*24 | F16: =MIN(D16,E16)*Assumptions!$B$16 | G16: =E16-F16 | H16: =Assumptions!$B$10*C16*B16 | I16: =MIN(H16,Assumptions!$B$5*Assumptions!$B$6*Assumptions!$B$7*Assumptions!$B$21*B16) | J16: =Assumptions!$B$5*Assumptions!$B$6*Assumptions!$B$7*Assumptions!$B$21*B16-I16 | K16: =Assumptions!$B$5*Assumptions!$B$6*Assumptions!$B$7*(24-Assumptions!$B$21)*B16 | L16: =(I16*Assumptions!$B$15+J16*Assumptions!$B$13+K16*Assumptions!$B$14)/100 | M16: =F16*Assumptions!$B$11*Assumptions!$B$12/100
A17: TOTAL | D17: =SUM(D5:D16) | E17: =SUM(E5:E16) | F17: =SUM(F5:F16) | G17: =SUM(G5:G16) | H17: =SUM(H5:H16) | I17: =SUM(I5:I16) | J17: =SUM(J5:J16) | K17: =SUM(K5:K16) | ... M17: =SUM(M5:M16)

Sheet Economics
A1: Economics — £100k poultry plant-room
A3: CAPITAL
A4: Compute capex (boxes) | B4: =Assumptions!$B$5*Assumptions!$B$18
A5: Dry-cooler (heat dump) | B5: =Assumptions!$B$20
A6: TOTAL CAPEX | B6: =B4+B5
A8: ANNUAL P&L
A9: Compute revenue (needs DEMAND) | B9: =Assumptions!$B$5*Assumptions!$B$8*Assumptions!$B$9*Assumptions!$B$7*8760
A10: Heat revenue (sold to house @ discount) | B10: =Monthly!$M$17
A11: − Power | B11: =-Monthly!$L$17
A12: − Maintenance | B12: =-B6*Assumptions!$B$17
A13: − Opex | B13: =-Assumptions!$B$5*Assumptions!$B$19
A14: NET £/yr | B14: =B9+B10+B11+B12+B13
A15: PAYBACK (months) | B15: =IF(B14>0,B6/B14*12,"loss")
A16: Return on capital (%/yr) | B16: =B14/B6
A18: HEAT SINK CHECK
A19: Heat sold (kWh/yr) | B19: =Monthly!$F$17
A20: =% of house's heat demand | B20: =Monthly!$F$17/Monthly!$D$17 | C20: tiny % → room to scale far past £100k
A21: House saving (their incentive, £/yr) | B21: =Monthly!$M$17/Assumptions!$B$12*(1-Assumptions!$B$12) | C21: what halving their fuel bill is worth to them
A23: QUICK SCENARIOS (fuel × power, 90% contracted util)
A24: set Assumptions util=90%, then read:
A25: LPG + grid 24p ≈ 29mo · LPG + solar ≈ 21mo
A26: Oil + solar ≈ 21mo · Biomass + solar ≈ 22mo (heat cheap, solar carries it)
A27: At 70% util add ~8–10 months. Spot demand (55%) fails — DEMAND is still the gate.

Sheet Demand
A1: Demand — the one thing everything rests on
A2: Hard numbers (researched Jun 2026). Revenue is COMMODITY; token-serving ≈ raw rental. Utilisation is the variable that decides it, and your EDGE is being the lowest-cost producer.
A4: A · Revenue per 4090 is commodity — token does NOT beat raw rental
A5: Raw spot rental (Vast, host receives) | B5: £0.25/hr | C5: what you get renting the bare GPU
A6: Token-serve Llama-8B @ $0.03/M, ~1,750 tok/s batched | B6: ~£0.15–0.21/hr | C6: output @ commodity floor — LESS than raw rental
A7: Token-serve 70B (2×4090) @ ~$0.19/M | B7: ~£0.16/hr per GPU | C7: bigger model, lower throughput — no better
A8: → conclusion | B8: commodity ~£0.20–0.25/hr | C8: inference is a race to the floor; batching ≠ more £
A11: B · So UTILISATION decides it — what you need at the poultry site (£95k, 12.4p power, heat sold)
A12: Utilisation | B12: Net £/yr | C12: Payback (mo) | D12: verdict
A13: 0.5 | B13: 29126 | C13: 39.2 | D13: fails (chip dies)
A14: 0.55 | B14: 32605 | C14: 35 | D14: tight
A15: 0.65 | B15: 39562 | C15: 28.9 | D15: tight
A16: 0.7 | B16: 43040 | C16: 26.5 | D16: tight
A17: 0.8 | B17: 49998 | C17: 22.8 | D17: viable
A18: 0.9 | B18: 56955 | C18: 20.1 | D18: viable
A19: → Need ~55% just to beat the 3-yr chip life; ~77% for a 2-year payback. A 4090 gets ~55–65% on the open market.
A22: C · Your edge: lowest-cost producer (why you can WIN the utilisation)
A23: Your marginal cost (12.4p solar power) | B23: £0.056/GPU-hr | C23: cheapest
A24: A gamer's marginal cost (25p retail power) | B24: £0.113/GPU-hr | C24: 2× yours
A25: A datacentre's (grid + cooling + rent) | B25: £0.10–0.18/GPU-hr | C25: + overheads you don't have
A26: → you can price at the floor + still profit | B26: win routing (OpenRouter routes cheapest-first) | C26: heat + free siting = the margin others lack
A29: D · The three demand routes
A30: 1. Spot rental (Vast) + OpenRouter provider | B30: util ~55–70% (market) | C30: live in weeks; long tail of small providers IS listed; you're a price-taker
A31: 2. Be the CHEAPEST (your cost edge) → win routing | B31: util ~70–80% (push by price) | C31: the realistic plan — undercut on price, profit on low cost
A32: 3. One anchor customer (contract) | B32: util ~90% (locked) | C32: needs sales; a reason to pick you = your low price
A34: VALIDATE BEFORE THE £100k: run ONE box on Vast + OpenRouter for a month (~£2k). It measures the ONE unknown — real achievable utilisation at your price. If it clears ~65%, the £100k pays back; if it sits at 40%, it doesn't. That £2k de-risks the whole decision.

Sheet Notes
A1: Notes — the plant-room architecture
A3: FORM FACTOR: the compute unit IS a package plant room — external, like your biomass boiler house. Electronics stay OUTSIDE the shed (dust/ammonia/humidity are hostile + biosecurity); only WATER goes into the existing wet loop. You already install exactly this.
A4: BASE-LOAD vs PEAK: compute runs 24/7 for revenue, so its heat is steady. The house wants a lot at chick placement (32–34°C brooding) and little once birds self-heat / between crops. So compute = BASE-LOAD heat; the existing biomass/LPG boiler stays as the PEAK/top-up. They coexist.
A5: DRY-COOLER (the one new bit): when the shed doesn't want heat (between crops, hot weather), the compute can't switch off — that's the revenue — so a dry cooler dumps the excess. ~£4k, essential. (A biomass boiler just modulates off; compute can't.)
A6: FUEL VALUE: best where you displace LPG (~12p) or oil (~8.5p). At houses already on cheap biomass (~5p) the heat earns little — but solar + compute demand still carry the payback (~22mo). Sort your contacts by fuel.
A7: THE BIG ROOF: a broiler house roof (~2,000 m²) holds ~300 kWp. You only need ~40 kWp to power the compute cheaply; the rest could power the farm or export — a separate solar investment, and the reason cheap power is EASY here.
A8: WHAT STILL GATES IT: install/access/form-factor are solved by your background. Payback still needs (1) a buyer for the compute (own token endpoint or one customer — 36 GPUs is fillable) and (2) cheap power (the roof). Heat is the sweetener + the siting deal, not the driver.
